Metadata-Version: 2.1
Name: gprubin
Version: 0.1.2
Summary: gprubin
Home-page: https://github.com/PFLeget/gprubin
Download-URL: https://github.com/PFLeget/gprubin/releases/tag/v0.1.2.zip
Author: PFLeget
License: BSD License
Classifier: Topic :: Scientific/Engineering :: Astronomy
Classifier: Intended Audience :: Science/Research
License-File: LICENCE
Requires-Dist: numpy
Requires-Dist: scipy
Requires-Dist: treegp>=1.2.0
Requires-Dist: jax
